pylnbits/DTOs/invoice_dto.py
pylnbits/__init__.py
pylnbits/config.py
pylnbits/invoices.py
pylnbits/lndhub.py
pylnbits/lnurl_p.py
pylnbits/lnurl_w.py
pylnbits/user_manager.py
pylnbits/user_wallet.py
pylnbits/utils.py
pylnbits-0.0.8.dist-info/LICENSE
pylnbits-0.0.8.dist-info/METADATA
pylnbits-0.0.8.dist-info/WHEEL
pylnbits-0.0.8.dist-info/RECORD
